ntnx_vmm_py_client/__init__.py
ntnx_vmm_py_client/api_client.py
ntnx_vmm_py_client/api_response.py
ntnx_vmm_py_client/configuration.py
ntnx_vmm_py_client/custom_retry.py
ntnx_vmm_py_client/rest.py
ntnx_vmm_py_client/api/__init__.py
ntnx_vmm_py_client/api/esxi_stats_api.py
ntnx_vmm_py_client/api/esxi_vm_api.py
ntnx_vmm_py_client/api/image_placement_policies_api.py
ntnx_vmm_py_client/api/image_rate_limit_policies_api.py
ntnx_vmm_py_client/api/images_api.py
ntnx_vmm_py_client/api/ovas_api.py
ntnx_vmm_py_client/api/stats_api.py
ntnx_vmm_py_client/api/template_placement_policies_api.py
ntnx_vmm_py_client/api/templates_api.py
ntnx_vmm_py_client/api/vm_anti_affinity_policies_api.py
ntnx_vmm_py_client/api/vm_api.py
ntnx_vmm_py_client/api/vm_guest_customization_profiles_api.py
ntnx_vmm_py_client/api/vm_host_affinity_policies_api.py
ntnx_vmm_py_client/api/vm_recovery_points_api.py
ntnx_vmm_py_client/api/vm_startup_policies_api.py
ntnx_vmm_py_client/models/__init__.py
ntnx_vmm_py_client/models/OneOfcommon/__init__.py
ntnx_vmm_py_client/models/OneOfcommon/v1/__init__.py
ntnx_vmm_py_client/models/OneOfcommon/v1/config/KVPairvalue.py
ntnx_vmm_py_client/models/OneOfcommon/v1/config/__init__.py
ntnx_vmm_py_client/models/OneOfdataprotection/__init__.py
ntnx_vmm_py_client/models/OneOfdataprotection/v4/__init__.py
ntnx_vmm_py_client/models/OneOfdataprotection/v4/common/BaseVmRecoveryPointapplication_consistent_properties.py
ntnx_vmm_py_client/models/OneOfdataprotection/v4/common/__init__.py
ntnx_vmm_py_client/models/OneOfvmm/__init__.py
ntnx_vmm_py_client/models/OneOfvmm/v4/__init__.py
ntnx_vmm_py_client/models/OneOfvmm/v4/ahv/__init__.py
ntnx_vmm_py_client/models/OneOfvmm/v4/ahv/config/AddVmCustomAttributesApiResponsedata.py
ntnx_vmm_py_client/models/OneOfvmm/v4/ahv/config/AddVmDiskCustomAttributesApiResponsedata.py
ntnx_vmm_py_client/models/OneOfvmm/v4/ahv/config/AssignIpApiResponsedata.py
ntnx_vmm_py_client/models/OneOfvmm/v4/ahv/config/AssignVmOwnerApiResponsedata.py
ntnx_vmm_py_client-4.2.1.dist-info/LICENSE.txt
ntnx_vmm_py_client-4.2.1.dist-info/METADATA
ntnx_vmm_py_client-4.2.1.dist-info/WHEEL
ntnx_vmm_py_client-4.2.1.dist-info/top_level.txt
ntnx_vmm_py_client-4.2.1.dist-info/RECORD
